cGrailSort.cp39-win_amd64.pyd
grailsort.cp39-win_amd64.pyd
GrailSort-1.2.2.dist-info/LICENSE
GrailSort-1.2.2.dist-info/METADATA
GrailSort-1.2.2.dist-info/WHEEL
GrailSort-1.2.2.dist-info/top_level.txt
GrailSort-1.2.2.dist-info/RECORD
