Metadata-Version: 2.1
Name: GrailSort
Version: 1.2.2
Summary: Cython wrapper around GrailSort (https://github.com/gaming32/GrailSort-Maintained)
Home-page: https://github.com/gaming32/grailsort
Author: Gaming32
Author-email: gaming32i64@gmail.com
License: License :: OSI Approved :: MIT License
Platform: UNKNOWN
